unfromm-0.2.1.dist-info/RECORD
unfromm-0.2.1.dist-info/DESCRIPTION.rst
unfromm-0.2.1.dist-info/top_level.txt
unfromm-0.2.1.dist-info/WHEEL
unfromm-0.2.1.dist-info/pydist.json
unfromm-0.2.1.dist-info/METADATA
unfromm/__init__.py
unfromm/word_frequency.txt
unfromm/profane_words.txt
